globalPrimePay/__init__.py
globalPrimePay/_nbdev.py
globalPrimePay/client.py
globalPrimePay/exceptions.py
globalPrimePay/helper.py
globalPrimePay-0.0.16.dist-info/LICENSE
globalPrimePay-0.0.16.dist-info/METADATA
globalPrimePay-0.0.16.dist-info/WHEEL
globalPrimePay-0.0.16.dist-info/top_level.txt
globalPrimePay-0.0.16.dist-info/RECORD
