Metadata-Version: 2.1
Name: globalPrimePay
Version: 0.0.16
Summary: template, plz check
Home-page: https://github.com/thanakijwanavit/globalPrimePay
Author: nic
Author-email: nwanavit@tenxor.sh
License: Apache Software License 2.0
Keywords: global prime pay payment sdk
Classifier: Development Status :: 3 - Alpha
Classifier: Intended Audience :: Developers
Classifier: Natural Language :: English
Classifier: Programming Language :: Python :: 3.8
Classifier: License :: OSI Approved :: Apache Software License
Requires-Python: >=3.8
License-File: LICENSE
Requires-Dist: sentry-sdk
